sasapy/__init__.py
sasapy-1.0.0.dist-info/LICENSE.txt
sasapy-1.0.0.dist-info/METADATA
sasapy-1.0.0.dist-info/WHEEL
sasapy-1.0.0.dist-info/top_level.txt
sasapy-1.0.0.dist-info/RECORD
