Metadata-Version: 2.1
Name: sasapy
Version: 1.0.0
Summary: this is test package for me.
Home-page: https://github.com/rhoboro/pythonbook
Author: sasahara
Author-email: sasahiro1204@icloud.com
License: UNKNOWN
Platform: UNKNOWN
Classifier: License :: OSI Approved :: MIT License
Classifier: Programming Language :: Python :: 3
Classifier: Programming Language :: Python :: 3.6
Classifier: Programming Language :: Python :: 3.7
Classifier: Programming Language :: Python :: 3.8
Classifier: Operating System :: OS Independent
Requires-Python: ~=3.6
